natpmp/__init__.py
natpmp/__main__.py
natpmp/client.py
NAT_PMP-1.3.2.dist-info/LICENSE
NAT_PMP-1.3.2.dist-info/METADATA
NAT_PMP-1.3.2.dist-info/WHEEL
NAT_PMP-1.3.2.dist-info/top_level.txt
NAT_PMP-1.3.2.dist-info/RECORD
